{
  "users": [
    {
      "email": "blowecle@gmail.com",
      "username": "blowecle",
      "password": "password",
      "firstName": "Brandon",
      "lastName": "Lowe",
      "isAdmin": true
    }
  ],
  "students": [
    {
      "email": "ethanmckenna@gmail.com",
      "username": "Ethan1",
      "password": "Epassword",
      "firstName": "Ethan",
      "lastName": "McKenna",
      "age": 11,
      "color": "orange",
      "userId": 12
    }
  ],
  "pages": [
    {
      "isFirstPage": true,
      "isLastPage": false,
      "id": 1,
      "content": "Id diam maecenas ultricies mi eget mauris pharetra et ultrices. Donec enim diam vulputate ut pharetra sit. Adipiscing enim eu turpis egestas pretium aenean pharetra magna ac. Lorem ipsum dolor sit amet, consectetur adipiscing elit, sed do eiusmod tempor incididunt ut labore et dolore magna aliqua.",
      "image": null,
      "type": "text",
      "previousPage": null,
      "nextPage": 2,
      "studentId": 1,
      "bookId": 1
    },
    {
      "isFirstPage": false,
      "isLastPage": false,
      "id": 2,
      "content": "Vestibulum mattis ullamcorper velit sed. Dignissim cras tincidunt lobortis feugiat vivamus at augue eget. Magna etiam tempor orci eu lobortis. Nisi scelerisque eu ultrices vitae auctor eu augue ut.",
      "image": null,
      "type": "text",
      "previousPage": 1,
      "nextPage": 3,
      "studentId": 1,
      "bookId": 1
    },
    {
      "isFirstPage": false,
      "isLastPage": false,
      "id": 3,
      "content": "Duis ultricies lacus sed turpis tincidunt id aliquet. Nisi scelerisque eu ultrices vitae auctor eu augue ut. Adipiscing enim eu turpis egestas pretium aenean pharetra magna ac.",
      "image": null,
      "type": "text",
      "previousPage": 2,
      "nextPage": 4,
      "studentId": 1,
      "bookId": 1
    },
    {
      "isFirstPage": false,
      "isLastPage": false,
      "id": 4,
      "content": "Et magnis dis parturient montes. Duis ultricies lacus sed turpis tincidunt id aliquet. Vestibulum mattis ullamcorper velit sed. Dolor sit amet consectetur adipiscing.",
      "image": null,
      "type": "text",
      "previousPage": 3,
      "nextPage": 5,
      "studentId": 1,
      "bookId": 1
    },
    {
      "isFirstPage": false,
      "isLastPage": false,
      "id": 5,
      "content": "Orci a scelerisque purus semper eget duis at tellus. Quisque egestas diam in arcu cursus euismod quis.",
      "image": null,
      "type": "text",
      "previousPage": 4,
      "nextPage": 6,
      "studentId": 1,
      "bookId": 1
    },
    {
      "isFirstPage": false,
      "isLastPage": false,
      "id": 6,
      "content": "Velit euismod in pellentesque massa placerat duis ultricies lacus. Vitae tempus quam pellentesque nec nam aliquam sem. Magna etiam tempor orci eu lobortis. Lorem ipsum dolor sit amet, consectetur adipiscing elit, sed do eiusmod tempor incididunt ut labore et dolore magna aliqua.",
      "image": null,
      "type": "text",
      "previousPage": 5,
      "nextPage": 7,
      "studentId": 1,
      "bookId": 1
    },
    {
      "isFirstPage": false,
      "isLastPage": false,
      "id": 7,
      "content": "Id diam maecenas ultricies mi eget mauris pharetra et ultrices. Sapien faucibus et molestie ac feugiat sed. Nibh venenatis cras sed felis eget velit aliquet sagittis id.",
      "image": null,
      "type": "text",
      "previousPage": 6,
      "nextPage": 8,
      "studentId": 1,
      "bookId": 1
    },
    {
      "isFirstPage": false,
      "isLastPage": false,
      "id": 8,
      "content": "Donec enim diam vulputate ut pharetra sit. Sapien faucibus et molestie ac feugiat sed.",
      "image": null,
      "type": "text",
      "previousPage": 7,
      "nextPage": 9,
      "studentId": 1,
      "bookId": 1
    },
    {
      "isFirstPage": false,
      "isLastPage": false,
      "id": 9,
      "content": "Duis ultricies lacus sed turpis tincidunt id aliquet. Nisi scelerisque eu ultrices vitae auctor eu augue ut. Sapien faucibus et molestie ac feugiat sed. Elit duis tristique sollicitudin nibh sit amet commodo nulla facilisi!",
      "image": null,
      "type": "text",
      "previousPage": 8,
      "nextPage": 10,
      "studentId": 1,
      "bookId": 1
    },
    {
      "isFirstPage": false,
      "isLastPage": false,
      "id": 10,
      "content": "Pulvinar pellentesque habitant morbi tristique. Enim nulla aliquet porttitor lacus luctus.",
      "image": null,
      "type": "text",
      "previousPage": 9,
      "nextPage": 11,
      "studentId": 1,
      "bookId": 1
    },
    {
      "isFirstPage": false,
      "isLastPage": false,
      "id": 11,
      "content": "Integer malesuada nunc vel risus commodo viverra maecenas accumsan lacus. In egestas erat imperdiet sed euismod. Nibh venenatis cras sed felis eget velit aliquet sagittis id. Pulvinar pellentesque habitant morbi tristique.",
      "image": null,
      "type": "text",
      "previousPage": 10,
      "nextPage": 12,
      "studentId": 1,
      "bookId": 1
    },
    {
      "isFirstPage": false,
      "isLastPage": false,
      "id": 12,
      "content": "Dignissim cras tincidunt lobortis feugiat vivamus at augue eget. Velit euismod in pellentesque massa placerat duis ultricies lacus. Ultrices neque ornare aenean euismod elementum nisi! Nisi scelerisque eu ultrices vitae auctor eu augue ut.",
      "image": null,
      "type": "text",
      "previousPage": 11,
      "nextPage": 13,
      "studentId": 1,
      "bookId": 1
    },
    {
      "isFirstPage": false,
      "isLastPage": false,
      "id": 13,
      "content": "Dignissim suspendisse in est ante in nibh mauris cursus? Velit euismod in pellentesque massa placerat duis ultricies lacus. Sapien faucibus et molestie ac feugiat sed. Integer malesuada nunc vel risus commodo viverra maecenas accumsan lacus.",
      "image": null,
      "type": "text",
      "previousPage": 12,
      "nextPage": 14,
      "studentId": 1,
      "bookId": 1
    },
    {
      "isFirstPage": false,
      "isLastPage": false,
      "id": 14,
      "content": "Dignissim suspendisse in est ante in nibh mauris cursus? Varius duis at consectetur lorem donec massa sapien. Vestibulum mattis ullamcorper velit sed.",
      "image": null,
      "type": "text",
      "previousPage": 13,
      "nextPage": 15,
      "studentId": 1,
      "bookId": 1
    },
    {
      "isFirstPage": false,
      "isLastPage": false,
      "id": 15,
      "content": "Donec enim diam vulputate ut pharetra sit. Magna etiam tempor orci eu lobortis.",
      "image": null,
      "type": "text",
      "previousPage": 14,
      "nextPage": 16,
      "studentId": 1,
      "bookId": 1
    },
    {
      "isFirstPage": false,
      "isLastPage": false,
      "id": 16,
      "content": "Integer malesuada nunc vel risus commodo viverra maecenas accumsan lacus. Adipiscing enim eu turpis egestas pretium aenean pharetra magna ac. Et magnis dis parturient montes. Orci a scelerisque purus semper eget duis at tellus.",
      "image": null,
      "type": "text",
      "previousPage": 15,
      "nextPage": 17,
      "studentId": 1,
      "bookId": 1
    },
    {
      "isFirstPage": false,
      "isLastPage": true,
      "id": 17,
      "content": "Condimentum lacinia quis vel eros donec ac. Varius duis at consectetur lorem donec massa sapien.",
      "image": null,
      "type": "text",
      "previousPage": 16,
      "nextPage": null,
      "studentId": 1,
      "bookId": 1
    }
  ],
  "tags": [
    {
      "name": "animals"
    },
    {
      "name": "cars"
    },
    {
      "name": "monsters"
    },
    {
      "name": "family"
    },
    {
      "name": "nature"
    },
    {
      "name": "funny"
    },
    {
      "name": "happy"
    },
    {
      "name": "scary"
    }
  ],
  "bookTags": [
    {
      "bookId": 1,
      "tagId": 6
    },
    {
      "bookId": 1,
      "tagId": 8
    }
  ]
}